rocrate/__init__.py
rocrate/_version.py
rocrate/cli.py
rocrate/memory_buffer.py
rocrate/metadata.py
rocrate/rocrate.py
rocrate/utils.py
rocrate/vocabs.py
rocrate/data/ro-crate.jsonld
rocrate/data/schema.jsonld
rocrate/model/__init__.py
rocrate/model/computationalworkflow.py
rocrate/model/computerlanguage.py
rocrate/model/contextentity.py
rocrate/model/creativework.py
rocrate/model/data_entity.py
rocrate/model/dataset.py
rocrate/model/entity.py
rocrate/model/file.py
rocrate/model/file_or_dir.py
rocrate/model/metadata.py
rocrate/model/person.py
rocrate/model/preview.py
rocrate/model/root_dataset.py
rocrate/model/softwareapplication.py
rocrate/model/testdefinition.py
rocrate/model/testinstance.py
rocrate/model/testservice.py
rocrate/model/testsuite.py
rocrate/templates/preview_template.html.j2
rocrate-0.14.1.dist-info/licenses/LICENSE
test/__init__.py
test/conftest.py
test/test_cli.py
test/test_jsonld.py
test/test_metadata.py
test/test_model.py
test/test_read.py
test/test_readwrite.py
test/test_test_metadata.py
test/test_utils.py
test/test_workflow_ro_crate.py
test/test_write.py
test/test_wrroc.py
rocrate-0.14.1.dist-info/METADATA
rocrate-0.14.1.dist-info/WHEEL
rocrate-0.14.1.dist-info/entry_points.txt
rocrate-0.14.1.dist-info/top_level.txt
rocrate-0.14.1.dist-info/RECORD
