Metadata-Version: 2.4
Name: rocrate
Version: 0.14.1
Summary: RO-Crate metadata generator/parser
Home-page: https://github.com/ResearchObject/ro-crate-py/
Download-URL: https://github.com/researchobject/ro-crate-py/archive/0.14.1.tar.gz
Author: Daniel Bauer, Eli Chadwick, Paul De Geest, Bert Droesbeke, Ignacio Eguinoa, Alban Gaignard, Matthias Hörtenhuber, Sebastiaan Huber, Bruno Kinoshita, Simone Leo, Luca Pireddu, Laura Rodríguez-Navas, Raül Sirvent, Stian Soiland-Reyes, Laurent Thomas
Author-email: stain@apache.org
License: Apache-2.0
Keywords: researchobject ro-crate ro metadata jsonld
Classifier: Operating System :: OS Independent
Classifier: Development Status :: 3 - Alpha
Classifier: Intended Audience :: Developers
Classifier: Intended Audience :: Information Technology
Classifier: Topic :: Software Development :: Libraries
Classifier: Programming Language :: Python :: 3
Classifier: Programming Language :: Python :: 3.9
Classifier: Programming Language :: Python :: 3.10
Classifier: Programming Language :: Python :: 3.11
Classifier: Programming Language :: Python :: 3.12
Classifier: Topic :: Internet
Classifier: Topic :: Internet :: WWW/HTTP
Classifier: Topic :: System :: Archiving
Classifier: Topic :: System :: Archiving :: Packaging
Requires-Python: >=3.9
License-File: LICENSE
Requires-Dist: requests
Requires-Dist: arcp==0.2.1
Requires-Dist: jinja2
Requires-Dist: python-dateutil
Requires-Dist: click
Provides-Extra: ga2cwl
Requires-Dist: galaxy2cwl; extra == "ga2cwl"
Dynamic: author
Dynamic: author-email
Dynamic: classifier
Dynamic: description
Dynamic: description-content-type
Dynamic: download-url
Dynamic: home-page
Dynamic: keywords
Dynamic: license
Dynamic: license-file
Dynamic: provides-extra
Dynamic: requires-dist
Dynamic: requires-python
Dynamic: summary
